{
    "source": "IndieWire",
    "tier": "major",
    "original_title": "‘Gail Daughtry’: Inside the 7-Day Writing Exercise That’s Produced Three Feature Films",
    "link": "https://www.indiewire.com/features/podcast/screenwriting-101-how-to-write-script-week-1235204436/",
    "image": "https://www.indiewire.com/wp-content/uploads/2026/07/GettyImages-2283048272.jpg?w=650",
    "title_kr": "‘Gail Daughtry’: Inside the 7-Day Writing Exercise That’s Produced Three Feature Films",
    "summary_kr": "AI 모델 일시적 과부하로 정보를 불러오지 못했습니다.",
    "content_kr": "본문 처리 중 오류가 발생했습니다. 잠시 후 다시 시도해 주세요.",
    "reddit_reaction_kr": "",
    "keywords": [],
    "why_it_matters_kr": "",
    "editorial_category": "stage_to_screen",
    "editorial_category_label": "Stage to Screen",
    "context_kr": "",
    "korean_reader_note_kr": "",
    "signal_keywords": [],
    "date": "Thu, 09 Jul 2026 21:00:00 +0000",
    "scraped_at": "2026-07-10 01:27:09",
    "id": "gail-daughtry-inside-the-7day-writing-exercise-thats-produced-three-feature-films"
}