{
    "source": "American Theatre",
    "tier": "indie",
    "original_title": "When Beck Did Beckett: The Last Days of a Living Theater Cofounder",
    "link": "https://www.americantheatre.org/2026/02/24/when-beck-did-beckett-the-last-days-of-a-living-theater-cofounder/",
    "image": "https://www.americantheatre.org/wp-content/uploads/julian-beck_living-theatre.jpg",
    "title_kr": "When Beck Did Beckett: The Last Days of a Living Theater Cofounder",
    "summary_kr": "AI 모델 일시적 과부하로 정보를 불러오지 못했습니다.",
    "content_kr": "본문 처리 중 오류가 발생했습니다. 잠시 후 다시 시도해 주세요.",
    "reddit_reaction_kr": "",
    "keywords": [],
    "date": "Tue, 24 Feb 2026 12:24:16 +0000",
    "scraped_at": "2026-02-25 07:54:35",
    "id": "when-beck-did-beckett-the-last-days-of-a-living-theater-cofounder"
}